sineps/__init__.py
sineps/__version__.py
sineps/_client.py
sineps/_config.py
sineps/_exceptions.py
sineps/_rest_adapter.py
sineps/_utils.py
sineps/_validate.py
sineps/filter_extractor.py
sineps/intent_router.py
sineps-0.0.21.dist-info/LICENSE
sineps-0.0.21.dist-info/METADATA
sineps-0.0.21.dist-info/WHEEL
sineps-0.0.21.dist-info/top_level.txt
sineps-0.0.21.dist-info/RECORD
