Metadata-Version: 2.1
Name: sineps
Version: 0.0.21
Summary: The official Python library for the sineps API
Home-page: 
Author: Ceres Technologies
Author-email: infosec@sineps.io
License: 
Platform: UNKNOWN
Requires-Python: >=3.6
License-File: LICENSE
Requires-Dist: requests >=2.24.0
Requires-Dist: aiohttp >=3.6.2
Requires-Dist: python-dateutil >=2.9.0
